radiospectra/__init__.py
radiospectra/_version.py
radiospectra/exceptions.py
radiospectra/mixins.py
radiospectra/spectrum.py
radiospectra/utils.py
radiospectra/version.py
radiospectra/data/README.rst
radiospectra/data/__init__.py
radiospectra/net/__init__.py
radiospectra/net/attrs.py
radiospectra/net/sources/__init__.py
radiospectra/net/sources/ecallisto.py
radiospectra/net/sources/eovsa.py
radiospectra/net/sources/ilofar.py
radiospectra/net/sources/psp.py
radiospectra/net/sources/rstn.py
radiospectra/net/sources/tests/__init__.py
radiospectra/net/sources/tests/test_ecallisto_client.py
radiospectra/net/sources/tests/test_eovsa_client.py
radiospectra/net/sources/tests/test_ilofar.py
radiospectra/net/sources/tests/test_psp_client.py
radiospectra/net/sources/tests/test_rstn_client.py
radiospectra/net/sources/tests/data/ecallisto_resp1.html.gz
radiospectra/net/sources/tests/data/ecallisto_resp2.html.gz
radiospectra/net/sources/tests/data/ecallisto_resp_alt_format.html
radiospectra/net/sources/tests/data/eovsa_resp1.html
radiospectra/net/sources/tests/data/eovsa_resp2.html
radiospectra/net/sources/tests/data/ilofar_resp1.html
radiospectra/net/sources/tests/data/ilofar_resp2.html
radiospectra/net/sources/tests/data/psp_resp1.html.gz
radiospectra/net/sources/tests/data/psp_resp2.html.gz
radiospectra/net/sources/tests/data/rstn_holloman.html
radiospectra/net/sources/tests/data/rstn_learmonth.html
radiospectra/net/sources/tests/data/rstn_san-vito.html
radiospectra/spectrogram/__init__.py
radiospectra/spectrogram/spectrogram_factory.py
radiospectra/spectrogram/spectrogrambase.py
radiospectra/spectrogram/sources/__init__.py
radiospectra/spectrogram/sources/callisto.py
radiospectra/spectrogram/sources/eovsa.py
radiospectra/spectrogram/sources/ilofar357.py
radiospectra/spectrogram/sources/psp_rfs.py
radiospectra/spectrogram/sources/rpw.py
radiospectra/spectrogram/sources/rstn.py
radiospectra/spectrogram/sources/swaves.py
radiospectra/spectrogram/sources/waves.py
radiospectra-0.6.1.dist-info/LICENSE.rst
radiospectra-0.6.1.dist-info/METADATA
radiospectra-0.6.1.dist-info/WHEEL
radiospectra-0.6.1.dist-info/top_level.txt
radiospectra-0.6.1.dist-info/RECORD
