Metadata-Version: 2.2
Name: radiospectra
Version: 0.6.1
Summary: Provide support for some type of radio spectra in solar physics.
Author-email: The SunPy Community <sunpy@googlegroups.com>
License: Copyright (c) 2024, The SunPy Community
Project-URL: Homepage, https://sunpy.org
Project-URL: Download, https://pypi.org/project/radiospectra
Requires-Python: >=3.10
License-File: LICENSE.rst
Requires-Dist: sunpy[net]>=6.0.0
Requires-Dist: numpy>1.24
Requires-Dist: matplotlib>=3.7
Requires-Dist: scipy>=1.10
Requires-Dist: cdflib>=0.3.20
Provides-Extra: tests
Requires-Dist: pytest; extra == "tests"
Requires-Dist: pytest-astropy; extra == "tests"
Requires-Dist: pytest-doctestplus; extra == "tests"
Requires-Dist: pytest-cov; extra == "tests"
Requires-Dist: pytest-xdist; extra == "tests"
Requires-Dist: sunpy-soar; extra == "tests"
Provides-Extra: docs
Requires-Dist: sphinx; extra == "docs"
Requires-Dist: sphinx-automodapi; extra == "docs"
Requires-Dist: sphinx-changelog; extra == "docs"
Requires-Dist: sphinx-gallery; extra == "docs"
Requires-Dist: sunpy-sphinx-theme; extra == "docs"
Requires-Dist: packaging; extra == "docs"
Provides-Extra: dev
Requires-Dist: radiospectra[docs,tests]; extra == "dev"
